bioskin/__init__.py
bioskin/bioskin.py
bioskin/bioskin_gui.py
bioskin/character.py
bioskin/reconstruct.py
bioskin/reconstruct_in_batches.py
bioskin/reconstruct_multiple.py
bioskin/train.py
bioskin/train_exposure_aware.py
bioskin/train_multiple.py
bioskin/train_multiple_exposure_aware.py
bioskin/apps/dataset_augment_skin_props.py
bioskin/apps/homogenize_skin.py
bioskin/apps/manifold_sampling.py
bioskin/apps/optimize_biomaps.py
bioskin/apps/optimize_color_correction.py
bioskin/dataset/__init__.py
bioskin/dataset/dataset_augment_illuminants.py
bioskin/dataset/dataset_bin2pt.py
bioskin/dataset/dataset_build_from_bins.py
bioskin/dataset/dataset_dump_tensors.py
bioskin/dataset/dataset_filter.py
bioskin/dataset/dataset_inspect.py
bioskin/dataset/dataset_smooth.py
bioskin/editing/__init__.py
bioskin/editing/operators.py
bioskin/lighting/__init__.py
bioskin/lighting/light_transport.py
bioskin/loss/__init__.py
bioskin/loss/log_losses.py
bioskin/loss/loss_functions.py
bioskin/parameters/__init__.py
bioskin/parameters/parameter.py
bioskin/parameters/parameter_differences.py
bioskin/parameters/params_io.py
bioskin/spectrum/__init__.py
bioskin/spectrum/color_spectrum.py
bioskin/spectrum/differential_color_distance_functions.py
bioskin/utils/__init__.py
bioskin/utils/create_GIF.py
bioskin/utils/io.py
bioskin/utils/plotting.py
bioskin/utils/tensorToCSV.py
bioskin-1.0.dist-info/LICENSE
bioskin-1.0.dist-info/METADATA
bioskin-1.0.dist-info/WHEEL
bioskin-1.0.dist-info/top_level.txt
bioskin-1.0.dist-info/RECORD
